Workbook
Name BUDGET_Title: Summary!$A$2
Name COMPANY_NAME: Summary!$A$1

Sheet Summary
A1: MOSMH
A2: MONTHLY BUDGET
B4: BUDGET TOTALS | C4: ESTIMATED | D4: PRIVATE | E4: ACTUAL | F4: DIFFERENCE
B5: Income | C5: =Summary!$C$23 -> 63300 | D5: =Summary!$C5*2 -> 126600 | E5: =Summary!$D$23 -> 57450 | F5: =Summary!$E5-Summary!$C5 -> -5850
B6: Expenses | C6: =Expenses!$C$25+Summary!$C$30 -> 54500 | D6: =Summary!$C6*2 -> 109000 | E6: =Expenses!$D$25+Summary!$D$30 -> 39775 | F6: =Summary!$E6-Summary!$C6 -> -14725
B8: Budget Overview chart is in this cell. Top 5 Operating Expenses are automatically updated in Top5Expenses table, below.
B9: WHAT ARE MY TOP 5 HIGHEST OPERATING EXPENSES?
B10: EXPENSE | C10: AMOUNT | D10: % OF EXPENSES | E10: 15% REDUCTION
B11: {=INDEX(Expenses!$B$5:$F$24,MATCH(Summary!$C11,Expenses!$E$5:$E$24,0),1)} -> Maintenance and repairs | C11: =LARGE(Expenses!$E$5:$E$24,1) -> 4600 | D11: =Summary!$C11/$E$6 -> 0.11565053 | E11: =Summary!$C11*0.15 -> 690
B12: {=INDEX(Expenses!$B$5:$F$24,MATCH(Summary!$C12,Expenses!$E$5:$E$24,0),1)} -> Supplies | C12: =LARGE(Expenses!$E$5:$E$24,2) -> 4500 | D12: =Summary!$C12/$E$6 -> 0.11313639 | E12: =Summary!$C12*0.15 -> 675
B13: {=INDEX(Expenses!$B$5:$F$24,MATCH(Summary!$C13,Expenses!$E$5:$E$24,0),1)} -> Taxes | C13: =LARGE(Expenses!$E$5:$E$24,3) -> 3200 | D13: =Summary!$C13/$E$6 -> 0.080452546 | E13: =Summary!$C13*0.15 -> 480
B14: {=INDEX(Expenses!$B$5:$F$24,MATCH(Summary!$C14,Expenses!$E$5:$E$24,0),1)} -> Advertising | C14: =LARGE(Expenses!$E$5:$E$24,4) -> 2500 | D14: =Summary!$C14/$E$6 -> 0.062853551 | E14: =Summary!$C14*0.15 -> 375
B15: {=INDEX(Expenses!$B$5:$F$24,MATCH(Summary!$C15,Expenses!$E$5:$E$24,0),1)} -> Interest | C15: =LARGE(Expenses!$E$5:$E$24,5) -> 2200 | D15: =Summary!$C15/$E$6 -> 0.055311125 | E15: =Summary!$C15*0.15 -> 330
B16: Total | C16: =SUBTOTAL(109,Summary!$C$11:$C$15) -> 17000 | D16: =SUBTOTAL(109,Summary!$D$11:$D$15) -> 0.42740415 | E16: =SUBTOTAL(109,Summary!$E$11:$E$15) -> 2550
B19: INCOME | C19: ESTIMATED | D19: ACTUAL | E19: TOP 5 AMOUNT | F19: DIFFERENCE
B20: Net sales | C20: 60000 | D20: 54000 | E20: =Summary!$D20+(10^-6)*ROW(Summary!$D20) -> 54000 | F20: =Summary!$D20-Summary!$C20 -> -6000
B21: Interest income | C21: 3000 | D21: 3000 | E21: =Summary!$D21+(10^-6)*ROW(Summary!$D21) -> 3000 | F21: =Summary!$D21-Summary!$C21 -> 0
B22: Asset sales (gain/loss) | C22: 300 | D22: 450 | E22: =Summary!$D22+(10^-6)*ROW(Summary!$D22) -> 450.00002 | F22: =Summary!$D22-Summary!$C22 -> 150
B23: Total Income | C23: =SUBTOTAL(109,Summary!$C$20:$C$22) -> 63300 | D23: =SUBTOTAL(109,Summary!$D$20:$D$22) -> 57450 | F23: =SUBTOTAL(109,Summary!$F$20:$F$22) -> -5850
B26: PERSONNEL EXPENSES | C26: ESTIMATED | D26: ACTUAL | E26: TOP 5 AMOUNT | F26: DIFFERENCE
B27: Wages | C27: 9500 | D27: 9600 | E27: =Summary!$D27+(10^-6)*ROW(Summary!$D27) -> 9600 | F27: =Summary!$C27-Summary!$D27 -> -100
B28: Employee benefits | C28: 4000 | D28: 0 | E28: =Summary!$D28+(10^-6)*ROW(Summary!$D28) -> 2.8e-05 | F28: =Summary!$C28-Summary!$D28 -> 4000
B29: Commission | C29: 5000 | D29: 4500 | E29: =Summary!$D29+(10^-6)*ROW(Summary!$D29) -> 4500 | F29: =Summary!$C29-Summary!$D29 -> 500
B30: Total Personnel Expenses | C30: =SUBTOTAL(109,Summary!$C$27:$C$29) -> 18500 | D30: =SUBTOTAL(109,Summary!$D$27:$D$29) -> 14100 | F30: =SUBTOTAL(109,Summary!$F$27:$F$29) -> 4400

Sheet Expenses
B1: =COMPANY_NAME -> MOSMH
B2: =BUDGET_Title -> MONTHLY BUDGET
B4: OPERATING EXPENSES | C4: ESTIMATED | D4: ACTUAL | E4: TOP 5 AMOUNT | F4: DIFFERENCE | I4: Missing values
B5: Advertising | C5: 3000 | D5: 2500 | E5: =Expenses!$D5+(10^-6)*ROW(Expenses!$D5) -> 2500 | F5: =Expenses!$C5-Expenses!$D5 -> 500
B6: Bad debts | C6: 2000 | E6: =Expenses!$D6+(10^-6)*ROW(Expenses!$D6) -> 6e-06
B7: Cash discounts | C7: 1500 | D7: 2175 | E7: =Expenses!$D7+(10^-6)*ROW(Expenses!$D7) -> 2175
B8: Delivery costs | C8: 2000 | D8: 1500 | E8: =Expenses!$D8+(10^-6)*ROW(Expenses!$D8) -> 1500
B9: Depreciation | C9: 1000 | E9: =Expenses!$D9+(10^-6)*ROW(Expenses!$D9) -> 9e-06
B10: Dues and subscriptions | C10: 500 | D10: 525 | E10: =Expenses!$D10+(10^-6)*ROW(Expenses!$D10) -> 525.00001
B11: Insurance | C11: 1300 | E11: =Expenses!$D11+(10^-6)*ROW(Expenses!$D11) -> 1.1e-05
B12: Interest | C12: 2000 | D12: 2200 | E12: =Expenses!$D12+(10^-6)*ROW(Expenses!$D12) -> 2200
B13: Legal and auditing | C13: 1000 | E13: =Expenses!$D13+(10^-6)*ROW(Expenses!$D13) -> 1.3e-05
B14: Maintenance and repairs | C14: 4500 | D14: 4600 | E14: =Expenses!$D14+(10^-6)*ROW(Expenses!$D14) -> 4600
B15: Office supplies | C15: 800 | D15: 750 | E15: =Expenses!$D15+(10^-6)*ROW(Expenses!$D15) -> 750.00001
B16: Postage | C16: 400 | D16: 350 | E16: =Expenses!$D16+(10^-6)*ROW(Expenses!$D16) -> 350.00002
B17: Rent or mortgage | C17: 4100 | E17: =Expenses!$D17+(10^-6)*ROW(Expenses!$D17) -> 1.7e-05
B18: Sales expenses | C18: 350 | D18: 400 | E18: =Expenses!$D18+(10^-6)*ROW(Expenses!$D18) -> 400.00002
B19: Shipping and storage | C19: 900 | D19: 840 | E19: =Expenses!$D19+(10^-6)*ROW(Expenses!$D19) -> 840.00002
B20: Supplies | C20: 5000 | D20: 4500 | E20: =Expenses!$D20+(10^-6)*ROW(Expenses!$D20) -> 4500
B21: Taxes | C21: 3000 | D21: 3200 | E21: =Expenses!$D21+(10^-6)*ROW(Expenses!$D21) -> 3200
B22: Telephone | C22: 250 | E22: =Expenses!$D22+(10^-6)*ROW(Expenses!$D22) -> 2.2e-05
B23: Utilities | C23: 1400 | D23: 1385 | E23: =Expenses!$D23+(10^-6)*ROW(Expenses!$D23) -> 1385
B24: Other | C24: 1000 | D24: 750 | E24: =Expenses!$D24+(10^-6)*ROW(Expenses!$D24) -> 750.00002
B25: Total Operating Expenses | C25: =SUBTOTAL(109,Expenses!$C$5:$C$24) -> 36000 | D25: =SUBTOTAL(109,Expenses!$D$5:$D$24) -> 25675 | F25: =SUBTOTAL(109,Expenses!$F$5:$F$24) -> 500
